<?xml version="1.0" encoding="UTF-8" standalone="yes"?>
<?xml-stylesheet type="text/xsl" href="#!-- #STYLESHEETS:ALP.xsl --#"?>

<DOCUMENT source-infobase-name="Rules" content-collection-id="NYCrules" source-infobase-title="The Rules of the City of New York" base-output-dir="D:\process\NFOProcess\codes\ny\newyorkcity\NYCrules\output\HUCCVLERTKEUARDR\" default-split-level="Chapter" makefile-filename="D:\process\NFOProcess\codes\ny\newyorkcity\NYCrules\output\HUCCVLERTKEUARDR\NYCrules.mak" css-stylesheet-href="#!-- #ID=NYCrules_css_id --#" xml-output-dir="D:\process\NFOProcess\codes\ny\newyorkcity\NYCrules\output\HUCCVLERTKEUARDR\XML\" css-stylesheet-name="NYCrules_css" makefile-document-depth="2">
	<LEVEL style-name="Chapter" style-name-escaped="Chapter" style-id="0-0-0-477" level-depth="2" toc-section="false">
		<RECORD id="0-0-0-43653" number="52536" version="3">
			<HEADING>Chapter 25: Service of Final Orders In Assisted Outpatient Treatment</HEADING>
			<PARA>
				<DESTINATION id="0-0-0-6221" name="T24C025"/>Chapter 25: Service of Final Orders In Assisted Outpatient Treatment</PARA>
		</RECORD>
		<LEVEL style-name="Subchapter" style-name-escaped="Subchapter" style-id="0-0-0-480" level-depth="3" toc-section="false">
			<LEVEL style-name="Subtitle" style-name-escaped="Subtitle" style-id="0-0-0-15301" level-depth="4" toc-section="false">
				<LEVEL style-name="Part" style-name-escaped="Part" style-id="0-0-0-483" level-depth="5" toc-section="false">
					<LEVEL style-name="Subpart" style-name-escaped="Subpart" style-id="0-0-0-15960" level-depth="6" toc-section="false">
						<LEVEL style-name="Section" style-name-escaped="Section" style-id="0-0-0-486" level-depth="7" toc-section="true">
							<RECORD id="0-0-0-43654" number="52537" version="3">
								<HEADING>§ 25-01 Introduction and Scope.</HEADING>
								<PARA>
									<DESTINATION id="0-0-0-6223" name="T24C025_25-01"/>§ 25-01 <CHARFORMAT bold="1" italic="0" underline="0" strike-out="0" hidden="0">Introduction and Scope.</CHARFORMAT>
								</PARA>
							</RECORD>
							<LEVEL style-name="Normal Level" style-name-escaped="Normal-Level" style-id="0-0-0-0" level-depth="0" toc-section="false">
								<RECORD id="0-0-0-43655" number="52538" version="3">
									<PARA>These rules apply to the service of final orders in the assisted outpatient treatment program within the City of New York.</PARA>
								</RECORD>
							</LEVEL>
						</LEVEL>
						<LEVEL style-name="Section" style-name-escaped="Section" style-id="0-0-0-486" level-depth="7" toc-section="true">
							<RECORD id="0-0-0-43656" number="52539" version="3">
								<HEADING>§ 25-02 Definitions and Construction of Words and Terms.</HEADING>
								<PARA>
									<DESTINATION id="0-0-0-6225" name="T24C025_25-02"/>§ 25-02 <CHARFORMAT bold="1" italic="0" underline="0" strike-out="0" hidden="0">Definitions and Construction of Words and Terms.</CHARFORMAT>
								</PARA>
							</RECORD>
							<LEVEL style-name="Normal Level" style-name-escaped="Normal-Level" style-id="0-0-0-0" level-depth="0" toc-section="false">
								<RECORD id="0-0-0-43657" number="52540" version="2512">
									<PARA>
										<TAB tab-count="1"/>(a)<TAB tab-count="1"/>
										<CHARFORMAT bold="1" italic="0" underline="0" strike-out="0" hidden="0">Act.</CHARFORMAT> &quot;Act&quot; shall mean the New York State Mental Hygiene Law § 9.60, as amended, entitled &quot;assisted outpatient treatment.&quot;</PARA>
								</RECORD>
								<RECORD id="0-0-0-43658" number="52541" version="3">
									<PARA>
										<TAB tab-count="1"/>(b)<TAB tab-count="1"/>
										<CHARFORMAT bold="1" italic="0" underline="0" strike-out="0" hidden="0">Inpatient Hospital Petitioner.</CHARFORMAT> &quot;Inpatient Hospital Petitioner&quot; shall mean the director of a hospital, or a designee of such director, who files a petition under the Act applying for a court order directing an individual who is hospitalized in such hospital at the time of the filing in court of such petition to receive assisted outpatient treatment under the Act.</PARA>
								</RECORD>
								<RECORD id="0-0-0-43659" number="52542" version="3">
									<PARA>
										<TAB tab-count="1"/>(c)<TAB tab-count="1"/>
										<CHARFORMAT bold="1" italic="0" underline="0" strike-out="0" hidden="0">Subject of the Petition.</CHARFORMAT> &quot;Subject of the Petition&quot; shall have the meaning set forth in § 9.60(a)(6) of the Act.</PARA>
								</RECORD>
							</LEVEL>
						</LEVEL>
						<LEVEL style-name="Section" style-name-escaped="Section" style-id="0-0-0-486" level-depth="7" toc-section="true">
							<RECORD id="0-0-0-43660" number="52543" version="3">
								<HEADING>§ 25-03 Service of Orders on a Subject of the Petition under the Act by Inpatient Hospital Petitioners.</HEADING>
								<PARA>
									<DESTINATION id="0-0-0-6227" name="T24C025_25-03"/>§ 25-03 <CHARFORMAT bold="1" italic="0" underline="0" strike-out="0" hidden="0">Service of Orders on a Subject of the Petition under the Act by Inpatient Hospital Petitioners.</CHARFORMAT>
								</PARA>
							</RECORD>
							<LEVEL style-name="Normal Level" style-name-escaped="Normal-Level" style-id="0-0-0-0" level-depth="0" toc-section="false">
								<RECORD id="0-0-0-43661" number="52544" version="2512">
									<PARA>
										<TAB tab-count="1"/>(a)<TAB tab-count="1"/>An Inpatient Hospital Petitioner shall promptly serve personally upon any individual who is the Subject of a Petition by such Petitioner any court orders issued under the Act pursuant to such petition.</PARA>
								</RECORD>
								<RECORD id="0-0-0-43662" number="52545" version="3">
									<PARA>
										<TAB tab-count="1"/>(b)<TAB tab-count="1"/>Such Inpatient Hospital Petitioner shall promptly provide to the Department, in such form as the Department requires, an affidavit that the requirements of subdivision (a) of this section have been met, with a copy of the court order so served.</PARA>
								</RECORD>
							</LEVEL>
						</LEVEL>
						<LEVEL style-name="Section" style-name-escaped="Section" style-id="0-0-0-486" level-depth="7" toc-section="true">
							<RECORD id="0-0-0-43663" number="52546" version="3">
								<HEADING>§ 25-04 Effect of Other Laws and Construction.</HEADING>
								<PARA>
									<DESTINATION id="0-0-0-6229" name="T24C025_25-04"/>§ 25-04 <CHARFORMAT bold="1" italic="0" underline="0" strike-out="0" hidden="0">Effect of Other Laws and Construction.</CHARFORMAT>
								</PARA>
							</RECORD>
							<LEVEL style-name="Normal Level" style-name-escaped="Normal-Level" style-id="0-0-0-0" level-depth="0" toc-section="false">
								<RECORD id="0-0-0-43664" number="52547" version="2512">
									<PARA>
										<TAB tab-count="1"/>(a)<TAB tab-count="1"/>These rules shall be read and enforced in accordance with all applicable provisions of law, including, but not limited to, the New York State Mental Hygiene Law.</PARA>
								</RECORD>
								<RECORD id="0-0-0-43665" number="52548" version="3">
									<PARA>
										<TAB tab-count="1"/>(b)<TAB tab-count="1"/>No provision herein shall limit the authority of the Department to take any other action it deems necessary, to enforce any provision of law within the jurisdiction of the Department.</PARA>
								</RECORD>
								<RECORD id="0-0-0-43666" number="52549" version="3">
									<PARA>
										<TAB tab-count="1"/>(c)<TAB tab-count="1"/>If any provision of this Chapter is adjudged invalid by any court of competent jurisdiction, such judgment shall not affect or impair the validity of the remainder of this Chapter.</PARA>
								</RECORD>
							</LEVEL>
						</LEVEL>
					</LEVEL>
				</LEVEL>
			</LEVEL>
		</LEVEL>
	</LEVEL>
</DOCUMENT>