<?xml version="1.0" encoding="UTF-8" standalone="yes"?>
<?xml-stylesheet type="text/xsl" href="#!-- #STYLESHEETS:ALP.xsl --#"?>

<DOCUMENT source-infobase-name="Rules" content-collection-id="NYCrules" source-infobase-title="The Rules of the City of New York" base-output-dir="D:\process\NFOProcess\codes\ny\newyorkcity\NYCrules\output\HUCCVLERTKEUARDR\" default-split-level="Chapter" makefile-filename="D:\process\NFOProcess\codes\ny\newyorkcity\NYCrules\output\HUCCVLERTKEUARDR\NYCrules.mak" css-stylesheet-href="#!-- #ID=NYCrules_css_id --#" xml-output-dir="D:\process\NFOProcess\codes\ny\newyorkcity\NYCrules\output\HUCCVLERTKEUARDR\XML\" css-stylesheet-name="NYCrules_css" makefile-document-depth="2">
	<LEVEL style-name="Chapter" style-name-escaped="Chapter" style-id="0-0-0-477" level-depth="2" toc-section="false">
		<RECORD id="0-0-0-140655" number="14849" version="2587">
			<HEADING>Chapter 32: High-Piled Combustible Storage</HEADING>
			<PARA>
				<DESTINATION id="0-0-0-1653" name="T03C032"/>Chapter 32: High-Piled Combustible Storage</PARA>
		</RECORD>
		<LEVEL style-name="Normal Level" style-name-escaped="Normal-Level" style-id="0-0-0-0" level-depth="0" toc-section="false">
			<RECORD id="0-0-0-140633" number="14850" version="2587">
				<PARA>
					<PARAFORMAT justify="center">(Amended City Record 9/20/2023, eff. 10/20/2023) <HIGHLIGHTER style="highlighter-ALP" original-style-name="ALP" style-name-escaped="highlighter-ALP" name="ALP" id="0-0-0-33">[ALP S-090]</HIGHLIGHTER>
					</PARAFORMAT>
				</PARA>
			</RECORD>
		</LEVEL>
		<LEVEL style-name="Subchapter" style-name-escaped="Subchapter" style-id="0-0-0-480" level-depth="3" toc-section="false">
			<LEVEL style-name="Subtitle" style-name-escaped="Subtitle" style-id="0-0-0-15301" level-depth="4" toc-section="false">
				<LEVEL style-name="Part" style-name-escaped="Part" style-id="0-0-0-483" level-depth="5" toc-section="false">
					<LEVEL style-name="Subpart" style-name-escaped="Subpart" style-id="0-0-0-15960" level-depth="6" toc-section="false">
						<LEVEL style-name="Section" style-name-escaped="Section" style-id="0-0-0-486" level-depth="7" toc-section="true">
							<RECORD id="0-0-0-140041" number="14851" version="2587">
								<HEADING>§ 3201 Reserved.</HEADING>
								<PARA>
									<DESTINATION id="0-0-0-18592" name="T03C032_3201"/>§ 3201 Reserved.</PARA>
							</RECORD>
						</LEVEL>
						<LEVEL style-name="Section" style-name-escaped="Section" style-id="0-0-0-486" level-depth="7" toc-section="true">
							<RECORD id="0-0-0-140635" number="14852" version="2587">
								<HEADING>§ 3202 Reserved.</HEADING>
								<PARA>
									<DESTINATION id="0-0-0-18594" name="T03C032_3202"/>§ 3202 Reserved.</PARA>
							</RECORD>
						</LEVEL>
						<LEVEL style-name="Section" style-name-escaped="Section" style-id="0-0-0-486" level-depth="7" toc-section="true">
							<RECORD id="0-0-0-140636" number="14853" version="2587">
								<HEADING>§ 3203 Reserved.</HEADING>
								<PARA>
									<DESTINATION id="0-0-0-18596" name="T03C032_3203"/>§ 3203 Reserved.</PARA>
							</RECORD>
						</LEVEL>
						<LEVEL style-name="Section" style-name-escaped="Section" style-id="0-0-0-486" level-depth="7" toc-section="true">
							<RECORD id="0-0-0-140637" number="14854" version="2587">
								<HEADING>§ 3204 Reserved.</HEADING>
								<PARA>
									<DESTINATION id="0-0-0-18598" name="T03C032_3204"/>§ 3204 Reserved.</PARA>
							</RECORD>
						</LEVEL>
						<LEVEL style-name="Section" style-name-escaped="Section" style-id="0-0-0-486" level-depth="7" toc-section="true">
							<RECORD id="0-0-0-140638" number="14855" version="2587">
								<HEADING>§ 3205 Reserved.</HEADING>
								<PARA>
									<DESTINATION id="0-0-0-18600" name="T03C032_3205"/>§ 3205 Reserved.</PARA>
							</RECORD>
						</LEVEL>
						<LEVEL style-name="Section" style-name-escaped="Section" style-id="0-0-0-486" level-depth="7" toc-section="true">
							<RECORD id="0-0-0-140639" number="14856" version="2587">
								<HEADING>§ 3206 Reserved.</HEADING>
								<PARA>
									<DESTINATION id="0-0-0-18602" name="T03C032_3206"/>§ 3206 Reserved.</PARA>
							</RECORD>
						</LEVEL>
						<LEVEL style-name="Section" style-name-escaped="Section" style-id="0-0-0-486" level-depth="7" toc-section="true">
							<RECORD id="0-0-0-140640" number="14857" version="2587">
								<HEADING>§ 3207 Reserved.</HEADING>
								<PARA>
									<DESTINATION id="0-0-0-18604" name="T03C032_3207"/>§ 3207 Reserved.</PARA>
							</RECORD>
						</LEVEL>
						<LEVEL style-name="Section" style-name-escaped="Section" style-id="0-0-0-486" level-depth="7" toc-section="true">
							<RECORD id="0-0-0-140641" number="14858" version="2587">
								<HEADING>§ 3208 Reserved.</HEADING>
								<PARA>
									<DESTINATION id="0-0-0-18606" name="T03C032_3208"/>§ 3208 Reserved.</PARA>
							</RECORD>
						</LEVEL>
						<LEVEL style-name="Section" style-name-escaped="Section" style-id="0-0-0-486" level-depth="7" toc-section="true">
							<RECORD id="0-0-0-140642" number="14859" version="2587">
								<HEADING>§ 3209 Reserved.</HEADING>
								<PARA>
									<DESTINATION id="0-0-0-18608" name="T03C032_3209"/>§ 3209 Reserved.</PARA>
							</RECORD>
						</LEVEL>
						<LEVEL style-name="Section" style-name-escaped="Section" style-id="0-0-0-486" level-depth="7" toc-section="true">
							<RECORD id="0-0-0-140643" number="14860" version="2587">
								<HEADING>§ 3210 Reserved.</HEADING>
								<PARA>
									<DESTINATION id="0-0-0-18610" name="T03C032_3210"/>§ 3210 Reserved.</PARA>
							</RECORD>
						</LEVEL>
					</LEVEL>
				</LEVEL>
			</LEVEL>
		</LEVEL>
	</LEVEL>
</DOCUMENT>